gather_code/__init__.py
gather_code/cli.py
gather_code-0.1.1.dist-info/LICENSE
gather_code-0.1.1.dist-info/METADATA
gather_code-0.1.1.dist-info/WHEEL
gather_code-0.1.1.dist-info/entry_points.txt
gather_code-0.1.1.dist-info/top_level.txt
gather_code-0.1.1.dist-info/RECORD
