Metadata-Version: 2.2
Name: gather_code
Version: 0.1.1
Summary: A tool to gather your codebase into a single file with a directory tree and file contents.
Home-page: https://github.com/ofurman/gather_code
Author: Oleksii Furman
Author-email: qizzup@gmail.com
Classifier: Programming Language :: Python :: 3
Classifier: License :: OSI Approved :: MIT License
Classifier: Operating System :: OS Independent
Requires-Python: >=3.6
License-File: LICENSE
Dynamic: author
Dynamic: author-email
Dynamic: classifier
Dynamic: home-page
Dynamic: requires-python
Dynamic: summary
